sycksec/__init__.py
sycksec/config.py
sycksec/core/__init__.py
sycksec/core/context.py
sycksec/core/crypto_utils.py
sycksec/core/obfuscation.py
sycksec/core/token_engine.py
sycksec/integrations/__init__.py
sycksec/integrations/django_auth.py
sycksec/integrations/django_backend.py
sycksec/integrations/flask_middleware.py
sycksec/security/__init__.py
sycksec/security/audit.py
sycksec/security/profiles.py
sycksec/utils/__init__.py
sycksec/utils/base64_utils.py
sycksec/utils/exceptions.py
sycksec/utils/helpers.py
sycksec/utils/validators.py
sycksec_token-1.0.0.dist-info/licenses/LICENSE
sycksec_token-1.0.0.dist-info/METADATA
sycksec_token-1.0.0.dist-info/WHEEL
sycksec_token-1.0.0.dist-info/entry_points.txt
sycksec_token-1.0.0.dist-info/top_level.txt
sycksec_token-1.0.0.dist-info/RECORD
