Metadata-Version: 2.4
Name: sycksec-token
Version: 1.0.0
Summary: Secure token generation and verification engine with rate limiting
Home-page: https://github.com/sycksec/sycksec-core
Author: Arjun Mani
Author-email: Arjun Mani <arjunmani45.mm@gmail.com>
Maintainer-email: Arjun Mani <arjunmani45.mm@gmail.com>
Project-URL: Homepage, https://github.com/sycksec/sycksec-core
Project-URL: Documentation, https://sycksec-core.readthedocs.io/
Project-URL: Repository, https://github.com/sycksec/sycksec-core.git
Project-URL: Issues, https://github.com/sycksec/sycksec-core/issues
Project-URL: Changelog, https://github.com/sycksec/sycksec-core/blob/main/CHANGELOG.md
Classifier: Development Status :: 4 - Beta
Classifier: Intended Audience :: Developers
Classifier: License :: OSI Approved :: MIT License
Classifier: Operating System :: OS Independent
Classifier: Programming Language :: Python :: 3
Classifier: Programming Language :: Python :: 3.8
Classifier: Programming Language :: Python :: 3.9
Classifier: Programming Language :: Python :: 3.10
Classifier: Programming Language :: Python :: 3.11
Classifier: Topic :: Security
Classifier: Topic :: Security :: Cryptography
Requires-Python: >=3.8
License-File: LICENSE
Requires-Dist: cryptography>=3.4.8
Requires-Dist: pycryptodome>=3.15.0
Provides-Extra: dev
Requires-Dist: pytest>=6.0; extra == "dev"
Requires-Dist: pytest-cov>=2.0; extra == "dev"
Requires-Dist: black>=22.0; extra == "dev"
Requires-Dist: flake8>=4.0; extra == "dev"
Requires-Dist: mypy>=0.950; extra == "dev"
Requires-Dist: pre-commit>=2.15; extra == "dev"
Provides-Extra: test
Requires-Dist: pytest>=6.0; extra == "test"
Requires-Dist: pytest-cov>=2.0; extra == "test"
Requires-Dist: pytest-mock>=3.6; extra == "test"
Dynamic: author
Dynamic: home-page
Dynamic: license-file
Dynamic: requires-python
